nobs/__init__.py
nobs/cli.py
nobs/docker.py
nobs/models.py
nobs/queue.py
nobs/runners.py
nobs/secrets.py
nobs/worker.py
nobs-0.1.13.dist-info/WHEEL
nobs-0.1.13.dist-info/entry_points.txt
nobs-0.1.13.dist-info/METADATA
nobs-0.1.13.dist-info/RECORD
